pddiansm/__init__.py
pddiansm/data/mappings/rxnorm_mappings.tsv
pddiansm/data/mappings/wikidata_mappings.tsv
pddiansm/data/thesauri/2016_01/substances2016.json
pddiansm/data/thesauri/2016_01/thesaurus2016.json
pddiansm/data/thesauri/2016_08/index_substances_82016.json
pddiansm/data/thesauri/2016_08/thesaurus_82016.json
pddiansm/data/thesauri/2018_05/index_substances_18_mars_2018.json
pddiansm/data/thesauri/2018_05/thesaurus_mars_2018.json
pddiansm/data/thesauri/2019_09/Thesaurus_09_2019.json
pddiansm/data/thesauri/2019_09/index_des_substances_09_2019.json
pddiansm/data/thesauri/2020_01/index-des-substances-20102020.json
pddiansm/data/thesauri/2020_01/thesaurus-referentiel-national-des-interactions-medicamenteuses-20102020.json
pddiansm/detected/PDDIdetected.py
pddiansm/detected/PDDIsimpleDrugsDetected.py
pddiansm/detected/__init__.py
pddiansm/detector/IPDDIdetector.py
pddiansm/detector/PDDIsimpleDrugsDetector.py
pddiansm/detector/PDDIthesaurusDetector.py
pddiansm/detector/__init__.py
pddiansm/mapper/AvailableIdentifierMappers.py
pddiansm/mapper/DefaultMapper.py
pddiansm/mapper/IMapper.py
pddiansm/mapper/MappingFile.py
pddiansm/mapper/__init__.py
pddiansm/pydantic/__init__.py
pddiansm/pydantic/interfaces_input.py
pddiansm/pydantic/interfaces_pddi.py
pddiansm/thesaurus/ISearchThesEntries.py
pddiansm/thesaurus/IThesauri.py
pddiansm/thesaurus/IThesaurus.py
pddiansm/thesaurus/IThesaurusEntriesFound.py
pddiansm/thesaurus/SearchThesEntries.py
pddiansm/thesaurus/ThesauriFiles.py
pddiansm/thesaurus/ThesauriJson.py
pddiansm/thesaurus/ThesaurusEntriesCollapsed.py
pddiansm/thesaurus/ThesaurusEntriesImp.py
pddiansm/thesaurus/ThesaurusExceptions.py
pddiansm/thesaurus/ThesaurusFiles.py
pddiansm/thesaurus/ThesaurusJson.py
pddiansm/thesaurus/__init__.py
pddiansm/utils/Singleton.py
pddiansm/utils/__init__.py
pddiansm/utils/normalize_string.py
tests/__init__.py
tests/test_detection.py
tests/test_detection_simple_drugs.py
tests/test_interfaces.py
tests/test_rxnorm_detection.py
pddiansm-0.2.0.dist-info/LICENSE
pddiansm-0.2.0.dist-info/METADATA
pddiansm-0.2.0.dist-info/WHEEL
pddiansm-0.2.0.dist-info/top_level.txt
pddiansm-0.2.0.dist-info/RECORD
