Metadata-Version: 2.1
Name: pddiansm
Version: 0.2.0
Summary: A package to detect potential drug drug interactions (PDDIs) according to the French National Agency for the Medicines and Health Products Safety (ANSM) guidelines
Home-page: https://github.com/scossin/pddiansm
Author: Sebastien Cossin
Author-email: cossin.sebastien@gmail.com
License: MIT
Platform: UNKNOWN
Requires-Dist: pydantic (~=1.7.3)
Requires-Dist: unidecode (~=1.1.1)
Requires-Dist: setuptools (~=46.1.3)
